localci/__init__.py
localci/__main__.py
localci/cli_utils.py
localci/git_utils.py
localci/platform_angular.py
localci/platform_interface.py
localci/platform_mvn.py
localci/platform_pypi.py
localci/platform_python.py
localci/version.py
localci-0.0.5.dist-info/METADATA
localci-0.0.5.dist-info/WHEEL
localci-0.0.5.dist-info/entry_points.txt
localci-0.0.5.dist-info/top_level.txt
localci-0.0.5.dist-info/RECORD
