Metadata-Version: 2.1
Name: localci
Version: 0.0.5
Summary: Makes local CI with Python, npm, and Java easy. Integrated with custom docker registry.
Home-page: UNKNOWN
Author: briccardo
Author-email: rbiagini02@gmail.com
License: MIT
Platform: UNKNOWN
Requires-Python: >=3.8
Requires-Dist: rich
Requires-Dist: pyfiglet
